bids_prov/visualize.py
bids_prov-0.1.0.dist-info/LICENSE
bids_prov-0.1.0.dist-info/METADATA
bids_prov-0.1.0.dist-info/WHEEL
bids_prov-0.1.0.dist-info/entry_points.txt
bids_prov-0.1.0.dist-info/RECORD
