Metadata-Version: 2.1
Name: bids_prov
Version: 0.1.0
Summary: BIDS extension proposal 28 : BIDS Provenance
License: CC-BY-4.0
Author: Camille Maumet
Requires-Python: >=3.10.0,<4.0.0
Classifier: Intended Audience :: Science/Research
Classifier: License :: Other/Proprietary License
Classifier: Programming Language :: Python :: 3
Classifier: Programming Language :: Python :: 3.10
Classifier: Programming Language :: Python :: 3.11
Classifier: Programming Language :: Python :: 3.12
Classifier: Topic :: Scientific/Engineering
Classifier: Topic :: Scientific/Engineering :: Medical Science Apps.
Requires-Dist: beautifulsoup4 (>=4.12.3,<5.0.0)
Requires-Dist: boutiques (>=0.5.26,<0.6.0)
Requires-Dist: click (>=8.1.7,<9.0.0)
Requires-Dist: deepdiff (>=7.0.1,<8.0.0)
Requires-Dist: graphviz (>=0.20.3,<0.21.0)
Requires-Dist: prov (>=2.0.0,<3.0.0)
Requires-Dist: pydot (>=2.0.0,<3.0.0)
Requires-Dist: pyld (>=2.0.4,<3.0.0)
Requires-Dist: pyyaml (>=6.0.1,<7.0.0)
Requires-Dist: rdflib (>=7.0.0,<8.0.0)
Requires-Dist: rdflib-jsonld (>=0.6.2,<0.7.0)
Requires-Dist: requests (>=2.32.3,<3.0.0)
